<?xml version="1.0"?>
<!DOCTYPE hibernate-mapping PUBLIC "-//Hibernate/Hibernate Mapping DTD 3.0//EN"
"http://hibernate.sourceforge.net/hibernate-mapping-3.0.dtd">
<!-- 
    Mapping file autogenerated by MyEclipse - Hibernate Tools
-->
<hibernate-mapping auto-import="true" default-lazy="true">
    <class name="org.opi.domain.Logon" table="LOGON" lazy="true">
        <id name="id" type="long">
            <column name="ID" precision="9" scale="0" />
            <generator class="sequence" />
        </id>
        <property name="username" type="string">
            <column name="USERNAME" length="10" />
        </property>
        <property name="pwd" type="string">
            <column name="PWD" length="10" />
        </property>
        <property name="email" type="string">
            <column name="EMAIL" length="40" not-null="true" />
        </property>
        <set name="individuals" inverse="true" lazy="true">
            <key>
                <column name="LOGONID" precision="9" scale="0" />
            </key>
            <one-to-many class="org.opi.domain.Individual" />
        </set>
        <set name="roles" inverse="true" lazy="true">
            <key>
                <column name="LOGONID" precision="9" scale="0" />
            </key>
            <one-to-many class="org.opi.domain.Role" />
        </set>
    </class>
</hibernate-mapping>
